License.txt
MANIFEST.in
README.txt
setup.cfg
setup.py
PyTraPaL.egg-info/PKG-INFO
PyTraPaL.egg-info/SOURCES.txt
PyTraPaL.egg-info/dependency_links.txt
PyTraPaL.egg-info/top_level.txt
PyTraPaL.egg-info/zip-safe
pytrapal/__init__.py
pytrapal/selectors.py